{
  "users": [
    {
      "name": "Astrid",
      "age": 25,
      "id": 1,
      "email": "astrid-hlavacek@hotmail.fr",
      "rating": 10
    },
    {
      "name": "Kévin",
      "age": 22,
      "id": 2,
      "email": "prepontkevin@gmail.com",
      "rating": 1
    },
    {
      "name": "Arnaud",
      "age": 24,
      "id": 13,
      "email": "arivo@hotmail.fr",
      "rating": 6
    },
    {
      "name": "Boris",
      "age": 19,
      "id": 17,
      "email": "boris@hotmail.fr",
      "rating": 2
    },
    {
      "name": "Thomas",
      "age": 35,
      "id": 19,
      "email": "tmoyse@gmail.com",
      "rating": 8
    },
    {
      "name": "Georges",
      "age": 80,
      "id": 20,
      "rating": 9
    }
  ],
  "sounds": [
    {
      "id": 1,
      "sound": "10415.mp3"
    },
    {
      "id": 2,
      "sound": "2639.mp3"
    },
    {
      "id": 3,
      "sound": "10425.mp3"
    },
    {
      "sound": "6114.mp3",
      "id": 4
    },
    {
      "sound": "10425.mp3",
      "id": 5
    },
    {
      "sound": "3634.mp3",
      "id": 6
    },
    {
      "sound": "4072.mp3",
      "id": 7
    },
    {
      "sound": "kick-tight.wav",
      "id": 8
    },
    {
      "sound": "snare-tape.wav",
      "id": 9
    },
    {
      "sound": "openhat-808.wav",
      "id": 10
    },
    {
      "sound": "kick-floppy.wav",
      "id": 11
    },
    {
      "sound": "tom-808.wav",
      "id": 12
    },
    {
      "sound": "hihat-ring.wav",
      "id": 13
    },
    {
      "sound": "crash-808.wav",
      "id": 14
    },
    {
      "sound": "clap-tape.wav",
      "id": 15
    },
    {
      "sound": "crash-noise.wav",
      "id": 16
    },
    {
      "sound": "cowbell-808.wav",
      "id": 17
    }
  ]
}